sapmanager/__init__.py
sapmanager/exceptions.py
sapmanager/main.py
sapmanager-1.2.4.dist-info/LICENSE
sapmanager-1.2.4.dist-info/METADATA
sapmanager-1.2.4.dist-info/WHEEL
sapmanager-1.2.4.dist-info/top_level.txt
sapmanager-1.2.4.dist-info/RECORD
