Metadata-Version: 2.1
Name: sapmanager
Version: 1.2.4
Summary: An unofficial library to run SAP logged into the selected ambient with the credentials provided, facilitating Scripting.
Home-page: https://github.com/SrRenks/sapmanager
Author: Ricardo Castro
Author-email: srrenks@gmail.com
License: MIT
License-File: LICENSE
Requires-Dist: pywin32
Requires-Dist: wheel
